[
  {
    "id": "reaper-sonne-usdc",
    "name": "USDC",
    "token": "USDC",
    "tokenAddress": "0x7f5c764cbc14f9669b88837ca1490cca17c31607",
    "tokenDecimals": 6,
    "earnedToken": "rf-soUSDC",
    "earnedTokenAddress": "0x1891a76d191d5a24bcd06dea4acadf4b8ae4b583",
    "earnContractAddress": "0x1891a76d191d5a24bcd06dea4acadf4b8ae4b583",
    "oracle": "tokens",
    "oracleId": "USDC",
    "status": "active",
    "platformId": "reaper",
    "assets": ["USDC"],
    "risks": [
      "COMPLEXITY_LOW",
      "BATTLE_TESTED",
      "IL_NONE",
      "MCAP_MICRO",
      "AUDIT",
      "CONTRACTS_VERIFIED"
    ],
    "strategyTypeId": "single",
    "buyTokenUrl": "https://app.1inch.io/#/10/simple/swap/ETH/USDC",
    "network": "optimism",
    "createdAt": 1682019849
  },
  {
    "id": "reaper-sonne-usdt",
    "name": "USDT",
    "token": "USDT",
    "tokenAddress": "0x94b008aa00579c1307b0ef2c499ad98a8ce58e58",
    "tokenDecimals": 6,
    "earnedToken": "rf-soUSDT",
    "earnedTokenAddress": "0xd84d315f22565399abfcb2b9c836955401c01a47",
    "earnContractAddress": "0xd84d315f22565399abfcb2b9c836955401c01a47",
    "oracle": "tokens",
    "oracleId": "USDT",
    "status": "active",
    "platformId": "reaper",
    "assets": ["USDT"],
    "risks": [
      "COMPLEXITY_LOW",
      "BATTLE_TESTED",
      "IL_NONE",
      "MCAP_MICRO",
      "AUDIT",
      "CONTRACTS_VERIFIED"
    ],
    "strategyTypeId": "single",
    "buyTokenUrl": "https://app.1inch.io/#/10/simple/swap/ETH/USDT",
    "network": "optimism",
    "createdAt": 1682019849
  },
  {
    "id": "reaper-sonne-dai",
    "name": "DAI",
    "token": "DAI",
    "tokenAddress": "0xda10009cbd5d07dd0cecc66161fc93d7c9000da1",
    "tokenDecimals": 18,
    "earnedToken": "rf-soDAI",
    "earnedTokenAddress": "0xc66b447be01ae5feadbd6dc76d228c5143af9a3c",
    "earnContractAddress": "0xc66b447be01ae5feadbd6dc76d228c5143af9a3c",
    "oracle": "tokens",
    "oracleId": "DAI",
    "status": "active",
    "platformId": "reaper",
    "assets": ["DAI"],
    "risks": [
      "COMPLEXITY_LOW",
      "BATTLE_TESTED",
      "IL_NONE",
      "MCAP_MICRO",
      "AUDIT",
      "CONTRACTS_VERIFIED"
    ],
    "strategyTypeId": "single",
    "buyTokenUrl": "https://app.1inch.io/#/10/simple/swap/ETH/DAI",
    "network": "optimism",
    "createdAt": 1682019849
  },
  {
    "id": "reaper-sonne-weth",
    "name": "WETH",
    "token": "WETH",
    "tokenAddress": "0x4200000000000000000000000000000000000006",
    "tokenDecimals": 18,
    "earnedToken": "rf-soWETH",
    "earnedTokenAddress": "0x932b30b2bc3f00b77affce8d0ff70b536f658462",
    "earnContractAddress": "0x932b30b2bc3f00b77affce8d0ff70b536f658462",
    "oracle": "tokens",
    "oracleId": "WETH",
    "status": "active",
    "platformId": "reaper",
    "assets": ["WETH"],
    "risks": [
      "COMPLEXITY_LOW",
      "BATTLE_TESTED",
      "IL_NONE",
      "MCAP_MICRO",
      "AUDIT",
      "CONTRACTS_VERIFIED"
    ],
    "strategyTypeId": "single",
    "buyTokenUrl": "https://app.1inch.io/#/10/simple/swap/ETH/WETH",
    "network": "optimism",
    "createdAt": 1682019849
  },
  {
    "id": "reaper-sonne-wbtc",
    "name": "WBTC",
    "token": "WBTC",
    "tokenAddress": "0x68f180fcce6836688e9084f035309e29bf0a2095",
    "tokenDecimals": 8,
    "earnedToken": "rf-soWBTC",
    "earnedTokenAddress": "0x42ab3ef2e6f8d625f4baf7724f35946c49a06b4f",
    "earnContractAddress": "0x42ab3ef2e6f8d625f4baf7724f35946c49a06b4f",
    "oracle": "tokens",
    "oracleId": "WBTC",
    "status": "active",
    "platformId": "reaper",
    "assets": ["WBTC"],
    "risks": [
      "COMPLEXITY_LOW",
      "BATTLE_TESTED",
      "IL_NONE",
      "MCAP_MICRO",
      "AUDIT",
      "CONTRACTS_VERIFIED"
    ],
    "strategyTypeId": "single",
    "buyTokenUrl": "https://app.1inch.io/#/10/simple/swap/ETH/WBTC",
    "network": "optimism",
    "createdAt": 1682019849
  },
  {
    "id": "reaper-sonne-susd",
    "name": "sUSD",
    "token": "sUSD",
    "tokenAddress": "0x8c6f28f2f1a3c87f0f938b96d27520d9751ec8d9",
    "tokenDecimals": 18,
    "earnedToken": "rf-soSUSD",
    "earnedTokenAddress": "0x89ac9cefc4e69b484fb46602964b38380fd19fb5",
    "earnContractAddress": "0x89ac9cefc4e69b484fb46602964b38380fd19fb5",
    "oracle": "tokens",
    "oracleId": "sUSD",
    "status": "active",
    "platformId": "reaper",
    "assets": ["sUSD"],
    "risks": [
      "COMPLEXITY_LOW",
      "BATTLE_TESTED",
      "IL_NONE",
      "MCAP_MICRO",
      "AUDIT",
      "CONTRACTS_VERIFIED"
    ],
    "strategyTypeId": "single",
    "buyTokenUrl": "https://app.1inch.io/#/10/simple/swap/ETH/sUSD",
    "network": "optimism",
    "createdAt": 1682019849
  },
  {
    "id": "reaper-sonne-op",
    "name": "OP",
    "token": "OP",
    "tokenAddress": "0x4200000000000000000000000000000000000042",
    "tokenDecimals": 18,
    "earnedToken": "rf-soOP",
    "earnedTokenAddress": "0x42cbc398f63855f89afe225f5f90151b00d6c73c",
    "earnContractAddress": "0x42cbc398f63855f89afe225f5f90151b00d6c73c",
    "oracle": "tokens",
    "oracleId": "OP",
    "status": "active",
    "platformId": "reaper",
    "assets": ["OP"],
    "risks": [
      "COMPLEXITY_LOW",
      "BATTLE_TESTED",
      "IL_NONE",
      "MCAP_MICRO",
      "AUDIT",
      "CONTRACTS_VERIFIED"
    ],
    "strategyTypeId": "single",
    "buyTokenUrl": "https://app.1inch.io/#/10/simple/swap/ETH/OP",
    "network": "optimism",
    "createdAt": 1682019849
  },
  {
    "id": "reaper-sonne-snx",
    "name": "SNX",
    "token": "SNX",
    "tokenAddress": "0x8700daec35af8ff88c16bdf0418774cb3d7599b4",
    "tokenDecimals": 18,
    "earnedToken": "rf-soSNX",
    "earnedTokenAddress": "0xaa27053c78cefe2bb96e7aca312062e67650ffe5",
    "earnContractAddress": "0xaa27053c78cefe2bb96e7aca312062e67650ffe5",
    "oracle": "tokens",
    "oracleId": "SNX",
    "status": "active",
    "platformId": "reaper",
    "assets": ["SNX"],
    "risks": [
      "COMPLEXITY_LOW",
      "BATTLE_TESTED",
      "IL_NONE",
      "MCAP_MICRO",
      "AUDIT",
      "CONTRACTS_VERIFIED"
    ],
    "strategyTypeId": "single",
    "buyTokenUrl": "https://app.1inch.io/#/10/simple/swap/ETH/SNX",
    "network": "optimism",
    "createdAt": 1682019849
  }
]
